audio_similarity/__init__.py
audio_similarity/__version__.py
audio_similarity/audio_similarity.py
Audio_Similarity-1.0.dist-info/LICENCE
Audio_Similarity-1.0.dist-info/METADATA
Audio_Similarity-1.0.dist-info/WHEEL
Audio_Similarity-1.0.dist-info/top_level.txt
Audio_Similarity-1.0.dist-info/RECORD
