Metadata-Version: 2.1
Name: Audio-Similarity
Version: 1.0
Summary: Audio similarity metrics for audio tasks
Home-page: https://github.com/markstent/audio-similarity
Download-URL: https://github.com/markstent/audio-similarity.git
Author: Mark Stent
Author-email: mark@markstent.co.za
License: MIT
Keywords: audio,similarity,audio similarity,swass,stent
Classifier: Development Status :: 5 - Production/Stable
Classifier: Intended Audience :: Developers
Classifier: Topic :: Software Development :: Build Tools
Classifier: License :: OSI Approved :: MIT License
Classifier: Programming Language :: Python
Classifier: Programming Language :: Python :: 3.8
Classifier: Programming Language :: Python :: 3.9
Classifier: Programming Language :: Python :: 3.10
Classifier: Programming Language :: Python :: 3.11
Requires-Python: >=3.9
License-File: LICENCE
Requires-Dist: numpy
Requires-Dist: librosa
Requires-Dist: pystoi
Requires-Dist: Pillow
Requires-Dist: matplotlib
Requires-Dist: soundfile
Requires-Dist: tqdm
